{
  "lastActive": "2026-02-26T15:52:34.080Z",
  "cliSessionId": "7775b79d-8e77-4dc9-816f-647c52a28841",
  "currentTask": "wf-b4f22cbe",
  "recentFiles": [],
  "recentDecisions": [],
  "contextSnapshot": {
    "keyFacts": [],
    "inProgress": "wf-websocket-gateway",
    "blockers": []
  },
  "metrics": {
    "tasksCompleted": 0,
    "filesModified": 0,
    "errorsEncountered": 0,
    "sessionCount": 0
  },
  "lastSessionSummary": null,
  "bypassTracking": {
    "count": 37,
    "attempts": [
      {
        "timestamp": "2026-02-23T15:06:51.264Z",
        "filePath": "/home/artem/Стільниця/2026/02/Projects/chat-microservice-2/.workflow/config.json",
        "operation": "write",
        "reason": "no_task_auto_create_disabled",
        "taskId": null
      },
      {
        "timestamp": "2026-02-23T15:08:23.047Z",
        "filePath": "/home/artem/Стільниця/2026/02/Projects/chat-microservice-2/.workflow/specs/product.md",
        "operation": "write",
        "reason": "no_task_auto_create_disabled",
        "taskId": null
      },
      {
        "timestamp": "2026-02-23T15:08:28.781Z",
        "filePath": "/home/artem/Стільниця/2026/02/Projects/chat-microservice-2/.workflow/specs/stack.md",
        "operation": "write",
        "reason": "no_task_auto_create_disabled",
        "taskId": null
      },
      {
        "timestamp": "2026-02-23T15:54:11.222Z",
        "filePath": "/home/artem/Стільниця/2026/02/Projects/chat-microservice-2/src/main.ts",
        "operation": "edit",
        "reason": "no_task_auto_create_disabled",
        "taskId": null
      },
      {
        "timestamp": "2026-02-23T16:21:47.350Z",
        "filePath": "/home/artem/Стільниця/2026/02/Projects/chat-microservice-2/src/exeption/error-interface.ts",
        "operation": "write",
        "reason": "no_task_auto_create_disabled",
        "taskId": null
      },
      {
        "timestamp": "2026-02-23T16:22:01.623Z",
        "filePath": "/home/artem/Стільниця/2026/02/Projects/chat-microservice-2/src/exeption/error-interface.ts",
        "operation": "write",
        "reason": "no_task_auto_create_disabled",
        "taskId": null
      },
      {
        "timestamp": "2026-02-23T16:56:22.482Z",
        "filePath": "/home/artem/Стільниця/2026/02/Projects/chat-microservice-2/src/common/decorators/local-api-property.decorator.ts",
        "operation": "write",
        "reason": "no_task_auto_create_disabled",
        "taskId": null
      },
      {
        "timestamp": "2026-02-23T16:57:57.726Z",
        "filePath": "/home/artem/Стільниця/2026/02/Projects/chat-microservice-2/src/common/decorators/local-api-property.spec.ts",
        "operation": "write",
        "reason": "no_task_auto_create_disabled",
        "taskId": null
      },
      {
        "timestamp": "2026-02-24T13:38:17.964Z",
        "filePath": "/home/artem/Стільниця/2026/02/Projects/chat-microservice-2/.workflow/config.json",
        "operation": "edit",
        "reason": "no_task_auto_create_disabled",
        "taskId": null
      },
      {
        "timestamp": "2026-02-24T13:45:02.962Z",
        "filePath": "/home/artem/Стільниця/2026/02/Projects/chat-microservice-2/.workflow/roadmap.md",
        "operation": "write",
        "reason": "no_task_auto_create_disabled",
        "taskId": null
      },
      {
        "timestamp": "2026-02-24T16:58:08.529Z",
        "filePath": "/home/artem/Стільниця/2026/02/Projects/chat-microservice-2/.workflow/roadmap.md",
        "operation": "edit",
        "reason": "no_task_auto_create_disabled",
        "taskId": null
      },
      {
        "timestamp": "2026-02-25T11:05:32.909Z",
        "filePath": "/home/artem/Стільниця/2026/02/Projects/chat-microservice-2/.workflow/config.json",
        "operation": "edit",
        "reason": "no_task_auto_create_disabled",
        "taskId": null
      },
      {
        "timestamp": "2026-02-25T11:18:27.587Z",
        "filePath": "/home/artem/Стільниця/2026/02/Projects/chat-microservice-2/src/chat-gateway/dto/join-room.dto.ts",
        "operation": "write",
        "reason": "no_task_auto_create_disabled",
        "taskId": null
      },
      {
        "timestamp": "2026-02-25T11:18:39.148Z",
        "filePath": "/home/artem/Стільниця/2026/02/Projects/chat-microservice-2/src/chat-gateway/chat.gateway.ts",
        "operation": "write",
        "reason": "no_task_auto_create_disabled",
        "taskId": null
      },
      {
        "timestamp": "2026-02-25T11:18:39.852Z",
        "filePath": "/home/artem/Стільниця/2026/02/Projects/chat-microservice-2/src/chat-gateway/chat-gateway.module.ts",
        "operation": "write",
        "reason": "no_task_auto_create_disabled",
        "taskId": null
      },
      {
        "timestamp": "2026-02-25T11:19:00.514Z",
        "filePath": "/home/artem/Стільниця/2026/02/Projects/chat-microservice-2/src/chat-gateway/dto/join-room.dto.ts",
        "operation": "write",
        "reason": "no_task_auto_create_disabled",
        "taskId": null
      },
      {
        "timestamp": "2026-02-25T11:19:12.248Z",
        "filePath": "/home/artem/Стільниця/2026/02/Projects/chat-microservice-2/src/chat-gateway/chat.gateway.ts",
        "operation": "write",
        "reason": "no_task_auto_create_disabled",
        "taskId": null
      },
      {
        "timestamp": "2026-02-25T11:19:12.369Z",
        "filePath": "/home/artem/Стільниця/2026/02/Projects/chat-microservice-2/src/chat-gateway/chat-gateway.module.ts",
        "operation": "write",
        "reason": "no_task_auto_create_disabled",
        "taskId": null
      },
      {
        "timestamp": "2026-02-25T11:21:07.111Z",
        "filePath": "/home/artem/Стільниця/2026/02/Projects/chat-microservice-2/src/message/message.module.ts",
        "operation": "edit",
        "reason": "no_task_auto_create_disabled",
        "taskId": null
      },
      {
        "timestamp": "2026-02-25T11:23:58.388Z",
        "filePath": "/home/artem/Стільниця/2026/02/Projects/chat-microservice-2/src/chat-gateway/chat-gateway.spec.ts",
        "operation": "write",
        "reason": "no_task_auto_create_disabled",
        "taskId": null
      },
      {
        "timestamp": "2026-02-25T11:29:00.184Z",
        "filePath": "/home/artem/Стільниця/2026/02/Projects/chat-microservice-2/.workflow/roadmap.md",
        "operation": "edit",
        "reason": "no_task_auto_create_disabled",
        "taskId": null
      },
      {
        "timestamp": "2026-02-26T08:58:56.709Z",
        "filePath": "/home/artem/Стільниця/2026/02/Projects/chat-microservice-2/.workflow/config.json",
        "operation": "edit",
        "reason": "no_task_auto_create_disabled",
        "taskId": null
      },
      {
        "timestamp": "2026-02-26T09:31:53.716Z",
        "filePath": "/home/artem/Стільниця/2026/02/Projects/chat-microservice-2/src/message/dto/mark-read.dto.ts",
        "operation": "write",
        "reason": "no_task_auto_create_disabled",
        "taskId": null
      },
      {
        "timestamp": "2026-02-26T09:36:29.290Z",
        "filePath": "/home/artem/Стільниця/2026/02/Projects/chat-microservice-2/.workflow/roadmap.md",
        "operation": "edit",
        "reason": "no_task_auto_create_disabled",
        "taskId": null
      },
      {
        "timestamp": "2026-02-26T10:14:16.985Z",
        "filePath": "/home/artem/Стільниця/2026/02/Projects/chat-microservice-2/.workflow/roadmap.md",
        "operation": "edit",
        "reason": "no_task_auto_create_disabled",
        "taskId": null
      },
      {
        "timestamp": "2026-02-26T10:26:14.878Z",
        "filePath": "/home/artem/Стільниця/2026/02/Projects/chat-microservice-2/.workflow/roadmap.md",
        "operation": "edit",
        "reason": "no_task_auto_create_disabled",
        "taskId": null
      },
      {
        "timestamp": "2026-02-26T10:37:47.332Z",
        "filePath": "/home/artem/Стільниця/2026/02/Projects/chat-microservice-2/.workflow/roadmap.md",
        "operation": "edit",
        "reason": "no_task_auto_create_disabled",
        "taskId": null
      },
      {
        "timestamp": "2026-02-26T10:49:59.876Z",
        "filePath": "/home/artem/Стільниця/2026/02/Projects/chat-microservice-2/test/conversation.e2e-spec.ts",
        "operation": "write",
        "reason": "no_task_auto_create_disabled",
        "taskId": null
      },
      {
        "timestamp": "2026-02-26T10:50:19.411Z",
        "filePath": "/home/artem/Стільниця/2026/02/Projects/chat-microservice-2/test/message.e2e-spec.ts",
        "operation": "write",
        "reason": "no_task_auto_create_disabled",
        "taskId": null
      },
      {
        "timestamp": "2026-02-26T10:50:34.482Z",
        "filePath": "/home/artem/Стільниця/2026/02/Projects/chat-microservice-2/test/participant.e2e-spec.ts",
        "operation": "write",
        "reason": "no_task_auto_create_disabled",
        "taskId": null
      },
      {
        "timestamp": "2026-02-26T10:50:54.029Z",
        "filePath": "/home/artem/Стільниця/2026/02/Projects/chat-microservice-2/test/websocket.e2e-spec.ts",
        "operation": "write",
        "reason": "no_task_auto_create_disabled",
        "taskId": null
      },
      {
        "timestamp": "2026-02-26T10:52:58.588Z",
        "filePath": "/home/artem/Стільниця/2026/02/Projects/chat-microservice-2/test/message.e2e-spec.ts",
        "operation": "edit",
        "reason": "no_task_auto_create_disabled",
        "taskId": null
      },
      {
        "timestamp": "2026-02-26T14:55:15.866Z",
        "filePath": "/home/artem/Стільниця/2026/02/Projects/chat-microservice-2/.workflow/specs/wf-db336127.md",
        "operation": "write",
        "reason": "no_task_auto_create_disabled",
        "taskId": null
      },
      {
        "timestamp": "2026-02-26T14:56:21.379Z",
        "filePath": "/home/artem/Стільниця/2026/02/Projects/chat-microservice-2/.workflow/specs/wf-db336127.md",
        "operation": "write",
        "reason": "no_task_auto_create_disabled",
        "taskId": null
      },
      {
        "timestamp": "2026-02-26T15:07:46.904Z",
        "filePath": "/home/artem/Стільниця/2026/02/Projects/chat-microservice-2/.workflow/roadmap.md",
        "operation": "edit",
        "reason": "no_task_auto_create_disabled",
        "taskId": null
      },
      {
        "timestamp": "2026-02-26T15:36:11.332Z",
        "filePath": "/home/artem/Стільниця/2026/02/Projects/chat-microservice-2/src/message/controllers/base.controller.ts",
        "operation": "write",
        "reason": "no_task_auto_create_disabled",
        "taskId": null
      },
      {
        "timestamp": "2026-02-26T15:38:14.377Z",
        "filePath": "/home/artem/Стільниця/2026/02/Projects/chat-microservice-2/src/mention/mention.spec.ts",
        "operation": "write",
        "reason": "no_task_auto_create_disabled",
        "taskId": null
      }
    ],
    "autoCreatedTasks": []
  }
}
